androidicon/__init__.py
androidicon/__main__.py
androidicon/androidicon.py
androidicon-1.0.3.dist-info/DESCRIPTION.rst
androidicon-1.0.3.dist-info/METADATA
androidicon-1.0.3.dist-info/RECORD
androidicon-1.0.3.dist-info/WHEEL
androidicon-1.0.3.dist-info/entry_points.txt
androidicon-1.0.3.dist-info/metadata.json
androidicon-1.0.3.dist-info/top_level.txt
