Metadata-Version: 2.0
Name: androidicon
Version: 1.0.3
Summary: Create Android icons
Home-page: https://github.com/CarloRodriguez/androidicon
Author: Carlo Eduardo Rodriguez Espino
Author-email: carloeduardorodriguez@gmail.com
License: GPL
Download-URL: https://github.com/CarloRodriguez/androidicon/archive/master.zip
Keywords: android icon icons resize
Platform: UNKNOWN
Classifier: Development Status :: 5 - Production/Stable
Classifier: Intended Audience :: Developers
Classifier: Topic :: Software Development :: Build Tools
Classifier: Programming Language :: Python :: 2.7
Requires-Dist: Pillow
